wd_tag_heatmap/__init__.py
wd_tag_heatmap/cli.py
wd_tag_heatmap/data.py
wd_tag_heatmap/generator.py
wd_tag_heatmap/models.py
wd_tag_heatmap/processing.py
wd_tag_heatmap/py.typed
wd_tag_heatmap/utils.py
wd_tag_heatmap-0.1.0.dist-info/licenses/LICENSE
wd_tag_heatmap-0.1.0.dist-info/METADATA
wd_tag_heatmap-0.1.0.dist-info/WHEEL
wd_tag_heatmap-0.1.0.dist-info/entry_points.txt
wd_tag_heatmap-0.1.0.dist-info/top_level.txt
wd_tag_heatmap-0.1.0.dist-info/RECORD
