Metadata-Version: 2.4
Name: wd-tag-heatmap
Version: 0.1.0
Summary: Generate attention heatmaps for WD Tagger models - visualize which parts of an image contribute to each tag
Author: WD Tag Heatmap Contributors
Maintainer-email: Your Name <your.email@example.com>
License: MIT
Project-URL: Homepage, https://github.com/yourusername/wd-tag-heatmap
Project-URL: Documentation, https://github.com/yourusername/wd-tag-heatmap#readme
Project-URL: Repository, https://github.com/yourusername/wd-tag-heatmap
Project-URL: Bug Tracker, https://github.com/yourusername/wd-tag-heatmap/issues
Keywords: image-tagging,heatmap,attention-visualization,wd-tagger,anime,booru
Classifier: Development Status :: 4 - Beta
Classifier: Intended Audience :: Developers
Classifier: License :: OSI Approved :: MIT License
Classifier: Programming Language :: Python :: 3
Classifier: Programming Language :: Python :: 3.8
Classifier: Programming Language :: Python :: 3.9
Classifier: Programming Language :: Python :: 3.10
Classifier: Programming Language :: Python :: 3.11
Classifier: Programming Language :: Python :: 3.12
Classifier: Topic :: Scientific/Engineering :: Artificial Intelligence
Classifier: Topic :: Multimedia :: Graphics
Requires-Python: >=3.8
License-File: LICENSE
Requires-Dist: torch>=2.0.0
Requires-Dist: torchvision>=0.15.0
Requires-Dist: timm>=0.9.0
Requires-Dist: pillow>=9.0.0
Requires-Dist: numpy>=1.21.0
Requires-Dist: pandas>=1.3.0
Requires-Dist: huggingface-hub>=0.16.0
Requires-Dist: safetensors>=0.3.0
Requires-Dist: colorcet>=3.0.0
Requires-Dist: matplotlib>=3.5.0
Requires-Dist: tqdm>=4.62.0
Provides-Extra: dev
Requires-Dist: pytest>=7.0.0; extra == "dev"
Requires-Dist: black>=22.0.0; extra == "dev"
Requires-Dist: ruff>=0.0.260; extra == "dev"
Requires-Dist: mypy>=0.990; extra == "dev"
Dynamic: license-file
